bitunix/__init__.py
bitunix/client.py
bitunix-0.1.2.dist-info/LICENSE
bitunix-0.1.2.dist-info/METADATA
bitunix-0.1.2.dist-info/WHEEL
bitunix-0.1.2.dist-info/top_level.txt
bitunix-0.1.2.dist-info/RECORD
