Metadata-Version: 2.1
Name: bitunix
Version: 0.1.2
Summary: An open source, unofficial Python client for the BitUnix cryptocurrency exchange API
Home-page: https://github.com/0xCherryBlueZu/bitunix
Author: 0xCherryBlue
Author-email: 0xCherryBlue@proton.me
Classifier: Development Status :: 3 - Alpha
Classifier: Intended Audience :: Developers
Classifier: License :: OSI Approved :: MIT License
Classifier: Operating System :: OS Independent
Classifier: Programming Language :: Python :: 3
Classifier: Programming Language :: Python :: 3.7
Classifier: Programming Language :: Python :: 3.8
Classifier: Programming Language :: Python :: 3.9
Classifier: Programming Language :: Python :: 3.10
Requires-Python: >=3.7
License-File: LICENSE
Requires-Dist: requests>=2.25.0
